plotly-stubs/__init__.pyi
plotly-stubs/basedatatypes.pyi
plotly-stubs/callbacks.pyi
plotly-stubs/py.typed
plotly-stubs/subplots.pyi
plotly-stubs/utils.pyi
plotly-stubs/colors/__init__.pyi
plotly-stubs/express/__init__.pyi
plotly-stubs/express/_chart_types.pyi
plotly-stubs/express/_stubs_helpers.pyi
plotly-stubs/express/colors/__init__.pyi
plotly-stubs/graph_objects/__init__.pyi
plotly-stubs/graph_objs/__init__.pyi
plotly-stubs/graph_objs/_bar.pyi
plotly-stubs/graph_objs/_box.pyi
plotly-stubs/graph_objs/_candlestick.pyi
plotly-stubs/graph_objs/_contour.pyi
plotly-stubs/graph_objs/_figure.pyi
plotly-stubs/graph_objs/_heatmap.pyi
plotly-stubs/graph_objs/_layout.pyi
plotly-stubs/graph_objs/_scatter.pyi
plotly-stubs/graph_objs/_surface.pyi
plotly-stubs/graph_objs/graph_objs_disabled.pyi
plotly-stubs/graph_objs/subplots.pyi
plotly-stubs/graph_objs/bar/__init__.pyi
plotly-stubs/graph_objs/bar/_stream.pyi
plotly-stubs/graph_objs/bar/selected/__init__.pyi
plotly-stubs/graph_objs/bar/selected/_marker.pyi
plotly-stubs/graph_objs/bar/selected/_textfont.pyi
plotly-stubs/graph_objs/bar/unselected/__init__.pyi
plotly-stubs/graph_objs/bar/unselected/_marker.pyi
plotly-stubs/graph_objs/bar/unselected/_textfont.pyi
plotly-stubs/graph_objs/barpolar/__init__.pyi
plotly-stubs/graph_objs/box/__init__.pyi
plotly-stubs/graph_objs/box/_line.pyi
plotly-stubs/graph_objs/box/selected/__init__.pyi
plotly-stubs/graph_objs/box/selected/_marker.pyi
plotly-stubs/graph_objs/box/unselected/__init__.pyi
plotly-stubs/graph_objs/box/unselected/_marker.pyi
plotly-stubs/graph_objs/candlestick/__init__.pyi
plotly-stubs/graph_objs/candlestick/_decreasing.pyi
plotly-stubs/graph_objs/candlestick/_hoverlabel.pyi
plotly-stubs/graph_objs/candlestick/_increasing.pyi
plotly-stubs/graph_objs/candlestick/_legendgrouptitle.pyi
plotly-stubs/graph_objs/candlestick/_line.pyi
plotly-stubs/graph_objs/candlestick/_stream.pyi
plotly-stubs/graph_objs/candlestick/decreasing/__init__.pyi
plotly_stubs-0.1.1.dist-info/METADATA
plotly_stubs-0.1.1.dist-info/WHEEL
plotly_stubs-0.1.1.dist-info/licenses/LICENSE
plotly_stubs-0.1.1.dist-info/RECORD
