Metadata-Version: 2.4
Name: plotly-stubs
Version: 0.1.1
Summary: Type stubs for plotly.
Project-URL: Homepage, https://github.com/ClaasRostock/plotly-stubs
Project-URL: Documentation, https://ClaasRostock.github.io/plotly-stubs/README.html
Project-URL: Repository, https://github.com/ClaasRostock/plotly-stubs.git
Project-URL: Issues, https://github.com/ClaasRostock/plotly-stubs/issues
Project-URL: Changelog, https://github.com/ClaasRostock/plotly-stubs/blob/main/CHANGELOG.md
Author-email: Claas Rostock <claas.rostock@dnv.com>
Maintainer-email: Claas Rostock <claas.rostock@dnv.com>
License: MIT License
License-File: LICENSE
Keywords: plotly,stubs,types
Classifier: Development Status :: 4 - Beta
Classifier: Environment :: Console
Classifier: Intended Audience :: Developers
Classifier: Intended Audience :: Science/Research
Classifier: License :: OSI Approved :: MIT License
Classifier: Operating System :: MacOS
Classifier: Operating System :: Microsoft :: Windows
Classifier: Operating System :: POSIX :: Linux
Classifier: Programming Language :: Python :: 3.11
Classifier: Programming Language :: Python :: 3.12
Classifier: Programming Language :: Python :: 3.13
Classifier: Programming Language :: Python :: 3.14
Classifier: Topic :: Scientific/Engineering
Classifier: Topic :: Software Development :: Libraries :: Python Modules
Requires-Python: <3.15,>=3.11
